[
  {
    "id": "lionelmessi_pvpv1_2019",
    "card_id": "lionelmessi_pvpv1_2019",
    "player_name": "MESSI",
    "season_text": "2018-19",
    "season_end": 2019,
    "series": "PBP",
    "country": "Argentina",
    "club": "Barcelona",
    "overall": 123,
    "gol": 75,
    "asist": 72,
    "regate": 71,
    "pase": 60,
    "def": 9,
    "image_url": "/cards/lionelmessi_pvpv1_2019.png"
  },
  {
    "id": "lionelmessi_pvpv1_2018",
    "card_id": "lionelmessi_pvpv1_2018",
    "player_name": "MESSI",
    "season_text": "2017-18",
    "season_end": 2018,
    "series": "PBP",
    "country": "Argentina",
    "club": "Barcelona",
    "overall": 120,
    "gol": 64,
    "asist": 65,
    "regate": 89,
    "pase": 60,
    "def": 11,
    "image_url": "/cards/lionelmessi_pvpv1_2018.png"
  },
  {
    "id": "lionelmessi_pvpv1_2017",
    "card_id": "lionelmessi_pvpv1_2017",
    "player_name": "MESSI",
    "season_text": "2016-17",
    "season_end": 2017,
    "series": "PBP",
    "country": "Argentina",
    "club": "Barcelona",
    "overall": 120,
    "gol": 76,
    "asist": 62,
    "regate": 68,
    "pase": 56,
    "def": 13,
    "image_url": "/cards/lionelmessi_pvpv1_2017.png"
  },
  {
    "id": "lionelmessi_pvpv1_2021",
    "card_id": "lionelmessi_pvpv1_2021",
    "player_name": "MESSI",
    "season_text": "2020-21",
    "season_end": 2021,
    "series": "PBP",
    "country": "Argentina",
    "club": "Barcelona",
    "overall": 112,
    "gol": 55,
    "asist": 63,
    "regate": 82,
    "pase": 66,
    "def": 9,
    "image_url": "/cards/lionelmessi_pvpv1_2021.png"
  },
  {
    "id": "lionelmessi_pvpv1_2020",
    "card_id": "lionelmessi_pvpv1_2020",
    "player_name": "MESSI",
    "season_text": "2019-20",
    "season_end": 2020,
    "series": "PBP",
    "country": "Argentina",
    "club": "Barcelona",
    "overall": 108,
    "gol": 46,
    "asist": 63,
    "regate": 95,
    "pase": 59,
    "def": 9,
    "image_url": "/cards/lionelmessi_pvpv1_2020.png"
  },
  {
    "id": "lionelmessi_pvpv1_2016",
    "card_id": "lionelmessi_pvpv1_2016",
    "player_name": "MESSI",
    "season_text": "2015-16",
    "season_end": 2016,
    "series": "PBP",
    "country": "Argentina",
    "club": "Barcelona",
    "overall": 107,
    "gol": 70,
    "asist": 51,
    "regate": 57,
    "pase": 58,
    "def": 6,
    "image_url": "/cards/lionelmessi_pvpv1_2016.png"
  },
  {
    "id": "neymar_pvpv1_2018",
    "card_id": "neymar_pvpv1_2018",
    "player_name": "NEYMAR",
    "season_text": "2017-18",
    "season_end": 2018,
    "series": "PBP",
    "country": "Brasil",
    "club": "PSG",
    "overall": 103,
    "gol": 48,
    "asist": 60,
    "regate": 82,
    "pase": 54,
    "def": 12,
    "image_url": "/cards/neymar_pvpv1_2018.png"
  },
  {
    "id": "neymar_pvpv1_2016",
    "card_id": "neymar_pvpv1_2016",
    "player_name": "NEYMAR",
    "season_text": "2015-16",
    "season_end": 2016,
    "series": "PBP",
    "country": "Brasil",
    "club": "Barcelona",
    "overall": 103,
    "gol": 44,
    "asist": 75,
    "regate": 69,
    "pase": 56,
    "def": 16,
    "image_url": "/cards/neymar_pvpv1_2016.png"
  },
  {
    "id": "neymar_pvpv1_2017",
    "card_id": "neymar_pvpv1_2017",
    "player_name": "NEYMAR",
    "season_text": "2016-17",
    "season_end": 2017,
    "series": "PBP",
    "country": "Brasil",
    "club": "Barcelona",
    "overall": 97,
    "gol": 29,
    "asist": 70,
    "regate": 87,
    "pase": 51,
    "def": 22,
    "image_url": "/cards/neymar_pvpv1_2017.png"
  },
  {
    "id": "edenhazard_pvpv1_2019",
    "card_id": "edenhazard_pvpv1_2019",
    "player_name": "EDEN HAZARD",
    "season_text": "2018-19",
    "season_end": 2019,
    "series": "PBP",
    "country": "Belgica",
    "club": "Chelsea",
    "overall": 95,
    "gol": 31,
    "asist": 76,
    "regate": 75,
    "pase": 58,
    "def": 11,
    "image_url": "/cards/edenhazard_pvpv1_2019.png"
  },
  {
    "id": "robertlewandowski_pvpv1_2020",
    "card_id": "robertlewandowski_pvpv1_2020",
    "player_name": "ROBERT LEWANDOWSKI",
    "season_text": "2019-20",
    "season_end": 2020,
    "series": "PBP",
    "country": "Polonia",
    "club": "Bayern",
    "overall": 92,
    "gol": 80,
    "asist": 33,
    "regate": 25,
    "pase": 41,
    "def": 11,
    "image_url": "/cards/robertlewandowski_pvpv1_2020.png"
  },
  {
    "id": "ousmanedembele_pvpv1_2025",
    "card_id": "ousmanedembele_pvpv1_2025",
    "player_name": "DEMBELE",
    "season_text": "2024-25",
    "season_end": 2025,
    "series": "PBP",
    "country": "Francia",
    "club": "PSG",
    "overall": 90,
    "gol": 54,
    "asist": 66,
    "regate": 29,
    "pase": 54,
    "def": 8,
    "image_url": "/cards/ousmanedembele_pvpv1_2025.png"
  },
  {
    "id": "kylianmbappe_pvpv1_2025",
    "card_id": "kylianmbappe_pvpv1_2025",
    "player_name": "MBAPPE",
    "season_text": "2024-25",
    "season_end": 2025,
    "series": "PBP",
    "country": "Francia",
    "club": "Real Madrid",
    "overall": 90,
    "gol": 61,
    "asist": 41,
    "regate": 48,
    "pase": 50,
    "def": 5,
    "image_url": "/cards/kylianmbappe_pvpv1_2025.png"
  },
  {
    "id": "raphinha_pvpv1_2025",
    "card_id": "raphinha_pvpv1_2025",
    "player_name": "RAPHINHA",
    "season_text": "2024-25",
    "season_end": 2025,
    "series": "PBP",
    "country": "Brasil",
    "club": "Barcelona",
    "overall": 90,
    "gol": 47,
    "asist": 78,
    "regate": 25,
    "pase": 50,
    "def": 20,
    "image_url": "/cards/raphinha_pvpv1_2025.png"
  },
  {
    "id": "cristianoronaldo_pvpv1_2016",
    "card_id": "cristianoronaldo_pvpv1_2016",
    "player_name": "CRISTIANO RONALDO",
    "season_text": "2015-16",
    "season_end": 2016,
    "series": "PBP",
    "country": "Portugal",
    "club": "Real Madrid",
    "overall": 88,
    "gol": 73,
    "asist": 39,
    "regate": 21,
    "pase": 47,
    "def": 7,
    "image_url": "/cards/cristianoronaldo_pvpv1_2016.png"
  },
  {
    "id": "lamineyamal_pvpv1_2025",
    "card_id": "lamineyamal_pvpv1_2025",
    "player_name": "LAMINE YAMAL",
    "season_text": "2024-25",
    "season_end": 2025,
    "series": "PBP",
    "country": "España",
    "club": "Barcelona",
    "overall": 87,
    "gol": 25,
    "asist": 47,
    "regate": 86,
    "pase": 51,
    "def": 23,
    "image_url": "/cards/lamineyamal_pvpv1_2025.png"
  },
  {
    "id": "kevindebruyne_pvpv1_2020",
    "card_id": "kevindebruyne_pvpv1_2020",
    "player_name": "DE BRUYNE",
    "season_text": "2019-20",
    "season_end": 2020,
    "series": "PBP",
    "country": "Belgica",
    "club": "City",
    "overall": 84,
    "gol": 24,
    "asist": 96,
    "regate": 25,
    "pase": 58,
    "def": 24,
    "image_url": "/cards/kevindebruyne_pvpv1_2020.png"
  },
  {
    "id": "neymar_pvpv1_2019",
    "card_id": "neymar_pvpv1_2019",
    "player_name": "NEYMAR",
    "season_text": "2018-19",
    "season_end": 2019,
    "series": "PBP",
    "country": "Brasil",
    "club": "PSG",
    "overall": 81,
    "gol": 42,
    "asist": 45,
    "regate": 49,
    "pase": 52,
    "def": 9,
    "image_url": "/cards/neymar_pvpv1_2019.png"
  },
  {
    "id": "neymar_pvpv1_2020",
    "card_id": "neymar_pvpv1_2020",
    "player_name": "NEYMAR",
    "season_text": "2019-20",
    "season_end": 2020,
    "series": "PBP",
    "country": "Brasil",
    "club": "PSG",
    "overall": 80,
    "gol": 34,
    "asist": 43,
    "regate": 66,
    "pase": 51,
    "def": 10,
    "image_url": "/cards/neymar_pvpv1_2020.png"
  },
  {
    "id": "cristianoronaldo_pvpv1_2018",
    "card_id": "cristianoronaldo_pvpv1_2018",
    "player_name": "CRISTIANO RONALDO",
    "season_text": "2017-18",
    "season_end": 2018,
    "series": "PBP",
    "country": "Portugal",
    "club": "Real Madrid",
    "overall": 79,
    "gol": 67,
    "asist": 30,
    "regate": 20,
    "pase": 45,
    "def": 6,
    "image_url": "/cards/cristianoronaldo_pvpv1_2018.png"
  },
  {
    "id": "neymar_pvpv1_2021",
    "card_id": "neymar_pvpv1_2021",
    "player_name": "NEYMAR",
    "season_text": "2020-21",
    "season_end": 2021,
    "series": "PBP",
    "country": "Brasil",
    "club": "PSG",
    "overall": 78,
    "gol": 31,
    "asist": 52,
    "regate": 56,
    "pase": 50,
    "def": 10,
    "image_url": "/cards/neymar_pvpv1_2021.png"
  },
  {
    "id": "mohamedsalah_pvpv1_2025",
    "card_id": "mohamedsalah_pvpv1_2025",
    "player_name": "SALAH",
    "season_text": "2024-25",
    "season_end": 2025,
    "series": "PBP",
    "country": "Egipto",
    "club": "Liverpool",
    "overall": 78,
    "gol": 48,
    "asist": 56,
    "regate": 24,
    "pase": 44,
    "def": 10,
    "image_url": "/cards/mohamedsalah_pvpv1_2025.png"
  },
  {
    "id": "cristianoronaldo_pvpv1_2020",
    "card_id": "cristianoronaldo_pvpv1_2020",
    "player_name": "CRISTIANO RONALDO",
    "season_text": "2019-20",
    "season_end": 2020,
    "series": "PBP",
    "country": "Portugal",
    "club": "Juventus",
    "overall": 77,
    "gol": 54,
    "asist": 33,
    "regate": 29,
    "pase": 52,
    "def": 7,
    "image_url": "/cards/cristianoronaldo_pvpv1_2020.png"
  },
  {
    "id": "viniciusjunior_pvpv1_2025",
    "card_id": "viniciusjunior_pvpv1_2025",
    "player_name": "VINÍCIUS JÚNIOR",
    "season_text": "2024-25",
    "season_end": 2025,
    "series": "PBP",
    "country": "Brasil",
    "club": "Real Madrid",
    "overall": 76,
    "gol": 31,
    "asist": 55,
    "regate": 49,
    "pase": 46,
    "def": 14,
    "image_url": "/cards/viniciusjunior_pvpv1_2025.png"
  },
  {
    "id": "cristianoronaldo_pvpv1_2017",
    "card_id": "cristianoronaldo_pvpv1_2017",
    "player_name": "CRISTIANO RONALDO",
    "season_text": "2016-17",
    "season_end": 2017,
    "series": "PBP",
    "country": "Portugal",
    "club": "Real Madrid",
    "overall": 74,
    "gol": 61,
    "asist": 29,
    "regate": 15,
    "pase": 46,
    "def": 6,
    "image_url": "/cards/cristianoronaldo_pvpv1_2017.png"
  },
  {
    "id": "cristianoronaldo_pvpv1_2021",
    "card_id": "cristianoronaldo_pvpv1_2021",
    "player_name": "CRISTIANO RONALDO",
    "season_text": "2020-21",
    "season_end": 2021,
    "series": "PBP",
    "country": "Portugal",
    "club": "Juventus",
    "overall": 73,
    "gol": 54,
    "asist": 26,
    "regate": 29,
    "pase": 47,
    "def": 5,
    "image_url": "/cards/cristianoronaldo_pvpv1_2021.png"
  },
  {
    "id": "neymar_pvpv1_2023",
    "card_id": "neymar_pvpv1_2023",
    "player_name": "NEYMAR",
    "season_text": "2022-23",
    "season_end": 2023,
    "series": "PBP",
    "country": "Brasil",
    "club": "PSG",
    "overall": 69,
    "gol": 33,
    "asist": 47,
    "regate": 25,
    "pase": 57,
    "def": 11,
    "image_url": "/cards/neymar_pvpv1_2023.png"
  },
  {
    "id": "viniciusjunior_pvpv1_2024",
    "card_id": "viniciusjunior_pvpv1_2024",
    "player_name": "VINÍCIUS JÚNIOR",
    "season_text": "2023-24",
    "season_end": 2024,
    "series": "PBP",
    "country": "Brasil",
    "club": "Real Madrid",
    "overall": 69,
    "gol": 39,
    "asist": 33,
    "regate": 44,
    "pase": 43,
    "def": 9,
    "image_url": "/cards/viniciusjunior_pvpv1_2024.png"
  },
  {
    "id": "cristianoronaldo_pvpv1_2019",
    "card_id": "cristianoronaldo_pvpv1_2019",
    "player_name": "CRISTIANO RONALDO",
    "season_text": "2018-19",
    "season_end": 2019,
    "series": "PBP",
    "country": "Portugal",
    "club": "Juventus",
    "overall": 68,
    "gol": 42,
    "asist": 37,
    "regate": 25,
    "pase": 50,
    "def": 6,
    "image_url": "/cards/cristianoronaldo_pvpv1_2019.png"
  },
  {
    "id": "neymar_pvpv1_2022",
    "card_id": "neymar_pvpv1_2022",
    "player_name": "NEYMAR",
    "season_text": "2021-22",
    "season_end": 2022,
    "series": "PBP",
    "country": "Brasil",
    "club": "PSG",
    "overall": 63,
    "gol": 24,
    "asist": 46,
    "regate": 31,
    "pase": 53,
    "def": 13,
    "image_url": "/cards/neymar_pvpv1_2022.png"
  },
  {
    "id": "lionelmessi_pvpv1_2022",
    "card_id": "lionelmessi_pvpv1_2022",
    "player_name": "MESSI",
    "season_text": "2021-22",
    "season_end": 2022,
    "series": "PBP",
    "country": "Argentina",
    "club": "PSG",
    "overall": 61,
    "gol": 18,
    "asist": 45,
    "regate": 37,
    "pase": 61,
    "def": 5,
    "image_url": "/cards/lionelmessi_pvpv1_2022.png"
  },
  {
    "id": "cristianoronaldo_pvpv1_2022",
    "card_id": "cristianoronaldo_pvpv1_2022",
    "player_name": "CRISTIANO RONALDO",
    "season_text": "2021-22",
    "season_end": 2022,
    "series": "PBP",
    "country": "Portugal",
    "club": "Manchester United",
    "overall": 54,
    "gol": 38,
    "asist": 22,
    "regate": 12,
    "pase": 46,
    "def": 4,
    "image_url": "/cards/cristianoronaldo_pvpv1_2022.png"
  }
]
