{"id":"rayancherki_pvpv1_2025","card_id":"rayancherki_pvpv1_2025","player_name":"Rayan Cherki","season_text":"2024-25","season_end":2025,"series":"PBP","country":"Francia","club":"Lyon","overall":72,"gol":20,"asist":73,"regate":35,"pase":56,"def":9,"scores":{"overall":71.56,"gol":20.41,"asist":72.83,"regate":34.79,"pase":55.9,"def":9.46},"image_url":"/cards/rayancherki_pvpv1_2025.webp?v=1780945220427-100142","face_url":"/player-faces/rayancherki_pvpv1_2025.webp?v=1781153494160-75978","stats":{"minutes":3218,"goals":13,"goals_per_90":0.36,"assists":21,"key_passes":128,"key_passes_per_90":3.7,"successful_dribbles":89,"successful_dribbles_per_90":2.6,"total_passes":1593,"total_passes_per_90":46.1,"pass_accuracy":84.1,"tackles":22,"tackles_per_90":0.6,"interceptions":11,"interceptions_per_90":0.3,"base_score":35.78,"visual_score":71.56},"metadata":{"schema_version":"1.1.0","formula_version":"pbp-v2","data_source_version":"puntuaciones-atacantes-v1","source_file":"PUNTUACIONES_ATACANTES.csv"}}